git_goose-0.14.3.dist-info/licenses/LICENSE
goose/__init__.py
goose/__main__.py
goose/_version.py
goose/asyncio.py
goose/config.py
goose/context.py
goose/environment.py
goose/executable_unit.py
goose/manifest.py
goose/orphan_environments.py
goose/parallel.py
goose/paths.py
goose/process.py
goose/py.typed
goose/scheduler.py
goose/targets.py
goose/_utils/__init__.py
goose/_utils/pydantic.py
goose/backend/__init__.py
goose/backend/base.py
goose/backend/index.py
goose/backend/node.py
goose/backend/python.py
goose/backend/system.py
goose/git/__init__.py
goose/git/pre_commit.py
goose/git/pre_push.py
goose/git/shared.py
goose/git/status.py
git_goose-0.14.3.dist-info/METADATA
git_goose-0.14.3.dist-info/WHEEL
git_goose-0.14.3.dist-info/entry_points.txt
git_goose-0.14.3.dist-info/top_level.txt
git_goose-0.14.3.dist-info/RECORD
