Metadata-Version: 2.4
Name: git-goose
Version: 0.14.3
Summary: A picky and eager Git hook runner.
Author-email: Anton Agestam <git@antonagestam.se>
License: BSD 3-Clause
Project-URL: Source Repository, https://github.com/antonagestam/goose
Classifier: Intended Audience :: Developers
Classifier: Operating System :: OS Independent
Classifier: Programming Language :: Python :: 3.14
Classifier: Development Status :: 4 - Beta
Classifier: Typing :: Typed
Requires-Python: <3.15,>=3.14
License-File: LICENSE
Requires-Dist: uv
Requires-Dist: pydantic
Requires-Dist: PyYAML
Requires-Dist: nodeenv
Requires-Dist: identify
Requires-Dist: typer
Requires-Dist: rich
Requires-Dist: shellingham
Provides-Extra: test
Requires-Dist: pytest; extra == "test"
Requires-Dist: pytest-asyncio; extra == "test"
Provides-Extra: docs
Requires-Dist: mkdocs; extra == "docs"
Requires-Dist: mike; extra == "docs"
Requires-Dist: mkdocs-material; extra == "docs"
Requires-Dist: markdown-include; extra == "docs"
Dynamic: license-file
